anyci/__init__.py
anyci/ctest_junit_formatter.py
anyci/ctest_junit_formatter.xsl
anyci/docker.py
anyci/noop.py
anyci/publish_github_release.py
anyci/run.sh
appveyor/__init__.py
appveyor/apply_mingw_path_fix.py
appveyor/cancel-queued-build.ps1
appveyor/enable-worker-remote-access.ps1
appveyor/install_cmake.py
appveyor/patch_vs2008.py
appveyor/rolling-build.ps1
appveyor/run-with-mingw.cmd
appveyor/run-with-visual-studio.cmd
appveyor/run.cmd
appveyor/tweak_environment.py
ci_addons/__init__.py
ci_addons/__main__.py
ci_addons/_version.py
circle/__init__.py
circle/install_cmake.py
scikit_ci_addons-0.25.0.dist-info/DESCRIPTION.rst
scikit_ci_addons-0.25.0.dist-info/METADATA
scikit_ci_addons-0.25.0.dist-info/RECORD
scikit_ci_addons-0.25.0.dist-info/WHEEL
scikit_ci_addons-0.25.0.dist-info/entry_points.txt
scikit_ci_addons-0.25.0.dist-info/metadata.json
scikit_ci_addons-0.25.0.dist-info/top_level.txt
travis/__init__.py
travis/enable-worker-remote-access.sh
travis/install_cmake.py
travis/install_pyenv.py
travis/run-with-pyenv.sh
windows/install-cmake.ps1
windows/install-flang.ps1
windows/install-git.ps1
windows/install-microsoft-visual-cpp-for-python27.ps1
windows/install-miniconda3.ps1
windows/install-ninja.ps1
windows/install-nsis.ps1
windows/install-openssh.ps1
windows/install-python-27-x64.ps1
windows/install-python-36-x64.ps1
windows/install-python.ps1
windows/install-svn.ps1
windows/install-utils.ps1
