Metadata-Version: 2.0
Name: scikit-ci-addons
Version: 0.25.0
Summary: scikit-ci-addons is a command line tool and a set of scripts useful to help drive the CI of projects leveraging services like Appveyor, CircleCI, or TravisCI.
Home-page: https://github.com/scikit-build/scikit-ci-addons
Author: The scikit-build team
Author-email: scikit-build@googlegroups.com
License: Apache
Keywords: CI Appveyor CircleCI Travis
Platform: UNKNOWN
Classifier: Development Status :: 3 - Alpha
Classifier: Environment :: Console
Classifier: Intended Audience :: Developers
Classifier: License :: OSI Approved :: Apache Software License
Classifier: Natural Language :: English
Classifier: Operating System :: OS Independent
Classifier: Programming Language :: Python :: 2
Classifier: Programming Language :: Python :: 2.7
Classifier: Programming Language :: Python :: 3
Classifier: Programming Language :: Python :: 3.4
Classifier: Programming Language :: Python :: 3.5
Classifier: Programming Language :: Python :: 3.6
Classifier: Programming Language :: Python :: 3.7
Classifier: Programming Language :: Python :: 3.8
Classifier: Topic :: Software Development :: Build Tools
Requires-Dist: githubrelease (>=1.5.7)
Requires-Dist: lxml; python_version < "3.8"
